paras_reader-0.0.1.dist-info/DESCRIPTION.rst
paras_reader-0.0.1.dist-info/METADATA
paras_reader-0.0.1.dist-info/RECORD
paras_reader-0.0.1.dist-info/WHEEL
paras_reader-0.0.1.dist-info/entry_points.txt
paras_reader-0.0.1.dist-info/metadata.json
paras_reader-0.0.1.dist-info/top_level.txt
reader/__init__.py
reader/__main__.py
reader/config.txt
reader/feed.py
reader/viewer.py
