Metadata-Version: 2.0
Name: paras-reader
Version: 0.0.1
Summary: Read the latest Real Python tutorials
Home-page: https://github.com/realpython/reader
Author: Real Python
Author-email: office@realpython.com
License: MIT
Platform: UNKNOWN
Classifier: License :: OSI Approved :: MIT License
Classifier: Programming Language :: Python :: 3
Classifier: Programming Language :: Python :: 3.7
Requires-Dist: feedparser
Requires-Dist: html2text
